{
  "version": 1,
  "ohos-module-entry": {
    "SELECT_TARGET": "default",
    "MODULE_BUILD_DIR": "D:\\NJU_Calendar_Importer_ArkTS\\entry\\build",
    "TARGETS": {
      "default": {
        "SOURCE_ROOT": "D:\\NJU_Calendar_Importer_ArkTS\\entry\\src\\main",
        "RESOURCES_PATH": [
          "D:\\NJU_Calendar_Importer_ArkTS\\entry\\src\\main\\resources"
        ],
        "BUILD_PATH": {
          "OUTPUT_PATH": "D:\\NJU_Calendar_Importer_ArkTS\\entry\\build\\default\\outputs\\default",
          "INTERMEDIA_PATH": "D:\\NJU_Calendar_Importer_ArkTS\\entry\\build\\default\\intermediates",
          "JS_ASSETS_PATH": "D:\\NJU_Calendar_Importer_ArkTS\\entry\\build\\default\\intermediates\\loader_out\\default",
          "JS_LITE_ASSETS_PATH": "D:\\NJU_Calendar_Importer_ArkTS\\entry\\build\\default\\intermediates\\loader_out_lite\\default",
          "RES_PATH": "D:\\NJU_Calendar_Importer_ArkTS\\entry\\build\\default\\intermediates\\res\\default",
          "RES_PROFILE_PATH": "D:\\NJU_Calendar_Importer_ArkTS\\entry\\build\\default\\intermediates\\res\\default\\resources\\base\\profile",
          "ETS_SUPER_VISUAL_PATH": "D:\\NJU_Calendar_Importer_ArkTS\\entry\\build\\default\\cache\\default\\default@CompileArkTS\\esmodule",
          "JS_SUPER_VISUAL_PATH": "D:\\NJU_Calendar_Importer_ArkTS\\entry\\build\\default\\cache\\default\\default@CompileJS\\jsbundle",
          "WORKER_LOADER": "D:\\NJU_Calendar_Importer_ArkTS\\entry\\build\\default\\intermediates\\loader\\default\\loader.json",
          "MANIFEST_JSON": "D:\\NJU_Calendar_Importer_ArkTS\\entry\\build\\default\\intermediates\\manifest\\default",
          "OUTPUT_METADATA_JSON": "D:\\NJU_Calendar_Importer_ArkTS\\entry\\build\\default\\intermediates\\hap_metadata\\default\\output_metadata.json",
          "SOURCE_MAP_DIR": "D:\\NJU_Calendar_Importer_ArkTS\\entry\\build\\default\\intermediates\\source_map\\default"
        },
        "BUILD_OPTION": {
          "debuggable": true
        }
      }
    },
    "BUILD_OPTION": {
      "default-default": {
        "debuggable": true,
        "copyFrom": "default"
      }
    },
    "BUILD_PROFILE_OPT": {
      "apiType": "stageMode",
      "buildOption": {},
      "targets": [
        {
          "name": "default"
        }
      ]
    },
    "BUILD_CACHE_DIR": ""
  },
  "ohos-project": {
    "SELECT_PRODUCT_NAME": "default",
    "MODULE_BUILD_DIR": "D:\\NJU_Calendar_Importer_ArkTS\\build",
    "BUNDLE_NAME": "com.mc121.njucalendarimporter",
    "VERSION_CODE": 1000000,
    "VERSION_NAME": "1.2.0",
    "BUILD_PATH": {
      "OUTPUT_PATH": "D:\\NJU_Calendar_Importer_ArkTS\\build\\outputs\\default"
    },
    "MODULES": [
      {
        "name": "entry",
        "srcPath": "D:\\NJU_Calendar_Importer_ArkTS\\entry",
        "targets": [
          {
            "name": "default",
            "applyToProducts": [
              "default"
            ]
          }
        ],
        "belongProjectPath": "D:\\NJU_Calendar_Importer_ArkTS"
      }
    ],
    "PROFILE_OPT": {
      "app": {
        "products": [
          {
            "name": "default",
            "signingConfig": "default",
            "compatibleSdkVersion": "6.0.2(22)",
            "targetSdkVersion": "6.0.2(22)",
            "compileSdkVersion": "6.0.2(22)",
            "runtimeOS": "HarmonyOS"
          }
        ],
        "buildModeSet": [
          {
            "name": "debug"
          },
          {
            "name": "release"
          }
        ],
        "signingConfigs": [
          {
            "name": "default",
            "type": "HarmonyOS",
            "material": {
              "certpath": "C:\\Users\\hp\\.ohos\\config\\default_NJU_Calendar_Importer_ArkTS_fKNh4q_d7TvD3G1GpQEu3Hgte2R2n_RfvqX31baEYds=.cer",
              "keyAlias": "debugKey",
              "keyPassword": "0000001BB8294275485288EF62171682FE9FF345866E772747FD4A74CE7467696DD304E28D7308012E60E1",
              "profile": "C:\\Users\\hp\\.ohos\\config\\default_NJU_Calendar_Importer_ArkTS_fKNh4q_d7TvD3G1GpQEu3Hgte2R2n_RfvqX31baEYds=.p7b",
              "signAlg": "SHA256withECDSA",
              "storeFile": "C:\\Users\\hp\\.ohos\\config\\default_NJU_Calendar_Importer_ArkTS_fKNh4q_d7TvD3G1GpQEu3Hgte2R2n_RfvqX31baEYds=.p12",
              "storePassword": "0000001B48C5856012D3330EBFA26B4EB2FD70A91115CF72321F5B42AA2D8417891240E16EA07321E79E88"
            }
          }
        ]
      },
      "modules": [
        {
          "name": "entry",
          "srcPath": "./entry",
          "targets": [
            {
              "name": "default",
              "applyToProducts": [
                "default"
              ]
            }
          ]
        }
      ]
    },
    "CONFIG_PROPERTIES": {
      "enableSignTask": true,
      "skipNativeIncremental": false,
      "hvigor.keepDependency": true
    },
    "OVERALL_PROJECT_PATHS": [
      "D:\\NJU_Calendar_Importer_ArkTS"
    ],
    "BUILD_CACHE_DIR": ""
  }
}